setup.cfg
setup.py
hnfb/__init__.py
hnfb/main.py
hnfb/utils.py
hnfb.egg-info/PKG-INFO
hnfb.egg-info/SOURCES.txt
hnfb.egg-info/dependency_links.txt
hnfb.egg-info/requires.txt
hnfb.egg-info/top_level.txt