Metadata-Version: 1.1
Name: hnfb
Version: 0.2
Summary: Hacker News Firebase API python wrapper
Home-page: https://github.com/joriskoris/hnfb
Author: Jorintas Butkus
Author-email: jorintasb@gmail.com
License: MIT
Download-URL: https://github.com/joriskoris/hnfb/tarball/0.1
Keywords: hn,hacker news
Platform: UNKNOWN
